tkinter_utils/__init__.py
tkinter_utils/core.py
tkinter_utils/example.py
tkinter_utils-1.4.dist-info/METADATA
tkinter_utils-1.4.dist-info/WHEEL
tkinter_utils-1.4.dist-info/top_level.txt
tkinter_utils-1.4.dist-info/RECORD
