Metadata-Version: 2.1
Name: tkinter_utils
Version: 1.4
Summary: 简单的tkinter包装库，可以快速地创建小型桌面应用。
License: MIT Licence
